django_rq_wrapper/__init__.py
django_rq_wrapper/apps.py
django_rq_wrapper/management/__init__.py
django_rq_wrapper/management/commands/__init__.py
django_rq_wrapper/management/commands/rqworkers.py
django_rq_wrapper-3.1.dist-info/LICENSE
django_rq_wrapper-3.1.dist-info/METADATA
django_rq_wrapper-3.1.dist-info/WHEEL
django_rq_wrapper-3.1.dist-info/top_level.txt
django_rq_wrapper-3.1.dist-info/RECORD
