Metadata-Version: 2.1
Name: django-rq-wrapper
Version: 3.1
Summary: Django management command to run multiple rq workers in one command and autoreload.
Home-page: https://github.com/istrategylabs/django-rq-wrapper
Author: ISL
Author-email: dev@isl.co
License: MIT
Keywords: django rq autoreload worker
Platform: UNKNOWN
Classifier: Topic :: Utilities
Classifier: License :: OSI Approved :: MIT License
Requires-Dist: django (>=1.8.0)
Requires-Dist: rq (>=0.5.5)
Requires-Dist: django-rq (>=0.9.2)
